flusso/__init__.py
flusso/async_result.py
flusso/functions.py
flusso/option.py
flusso/result.py
flusso/types.py
flusso/primitives/__init__.py
flusso/primitives/base.py
flusso/primitives/exceptions.py
test/__init__.py
test/test_async_result.py
test/test_functions.py
test/test_option.py
test/test_option_base.py
test/test_option_decorator.py
test/test_result.py
flusso-0.1.0.dist-info/LICENSE
flusso-0.1.0.dist-info/METADATA
flusso-0.1.0.dist-info/WHEEL
flusso-0.1.0.dist-info/top_level.txt
flusso-0.1.0.dist-info/RECORD
