Metadata-Version: 2.1
Name: flusso
Version: 0.1.0
Summary: Rust Inspired Type-Safe Errors and Missing Values for Python.
Home-page: https://github.com/gum-tech/flusso
Author: Tomiwa Adey
Author-email: tomiwa@tomiwaadey.com
License: MIT
Keywords: python,monad,rust,functional-programming,option,result
Classifier: Programming Language :: Python :: 3
Classifier: License :: OSI Approved :: MIT License
Classifier: Operating System :: OS Independent
Requires-Python: >=3.7
License-File: LICENSE
Provides-Extra: dev
Requires-Dist: pytest (>=7.0) ; extra == 'dev'
Requires-Dist: pytest-asyncio ; extra == 'dev'
Requires-Dist: twine (>=4.0.2) ; extra == 'dev'
